pyddd/__init__.py
pyddd/application/__init__.py
pyddd/application/abstractions.py
pyddd/application/application.py
pyddd/application/condition.py
pyddd/application/exceptions.py
pyddd/application/executor.py
pyddd/application/handler.py
pyddd/application/module.py
pyddd/application/retry/__init__.py
pyddd/application/retry/none.py
pyddd/application/retry/tc_retry.py
pyddd/application/signal_manager.py
pyddd/domain/__init__.py
pyddd/domain/command.py
pyddd/domain/entity.py
pyddd/domain/event.py
pyddd/domain/message.py
pyddd/infrastructure/__init__.py
pyddd/infrastructure/transport/__init__.py
pyddd/infrastructure/transport/asyncio/__init__.py
pyddd/infrastructure/transport/asyncio/domain/__init__.py
pyddd/infrastructure/transport/asyncio/domain/abstractions.py
pyddd/infrastructure/transport/asyncio/domain/ask_policy.py
pyddd/infrastructure/transport/asyncio/domain/consumer.py
pyddd/infrastructure/transport/asyncio/domain/notification.py
pyddd/infrastructure/transport/asyncio/domain/queue.py
pyddd/infrastructure/transport/asyncio/redis/__init__.py
pyddd/infrastructure/transport/asyncio/redis/pubsub/__init__.py
pyddd/infrastructure/transport/asyncio/redis/pubsub/publisher.py
pyddd/infrastructure/transport/asyncio/redis/pubsub/queue.py
pyddd/infrastructure/transport/asyncio/redis/stream_group/__init__.py
pyddd/infrastructure/transport/asyncio/redis/stream_group/handler.py
pyddd/infrastructure/transport/asyncio/redis/stream_group/publisher.py
pyddd/infrastructure/transport/asyncio/redis/stream_group/tracker_strategy.py
pyddd/infrastructure/transport/core/__init__.py
pyddd/infrastructure/transport/core/abstractions.py
pyddd/infrastructure/transport/core/event_factory.py
pyddd/infrastructure/transport/core/publisher.py
pyddd/infrastructure/transport/core/tracker.py
pyddd/infrastructure/transport/core/tracker_factory.py
pyddd/infrastructure/transport/core/value_objects.py
pyddd/infrastructure/transport/sync/__init__.py
pyddd/infrastructure/transport/sync/domain/__init__.py
ddd_python-0.7.7.dist-info/LICENSE
ddd_python-0.7.7.dist-info/METADATA
ddd_python-0.7.7.dist-info/WHEEL
ddd_python-0.7.7.dist-info/RECORD
