Metadata-Version: 2.1
Name: ddd-python
Version: 0.7.7
Summary: Domain-Driven Design for Python
License: MIT
Author: v.morugin
Author-email: vamorugin@gmail.com
Requires-Python: >=3.9,<4.0
Classifier: License :: OSI Approved :: MIT License
Classifier: Programming Language :: Python
Classifier: Programming Language :: Python :: 3
Classifier: Programming Language :: Python :: 3.9
Classifier: Programming Language :: Python :: 3.10
Classifier: Programming Language :: Python :: 3.11
Classifier: Programming Language :: Python :: 3.12
Classifier: Programming Language :: Python :: 3.13
Classifier: Topic :: Software Development :: Libraries
Requires-Dist: pydantic (>=1.10.4,<3.0.0)
Requires-Dist: redis[redis] (>=5.0.0)
Requires-Dist: tenacity[tenacity] (>=9.0.0)
